{
	"_meta": {
		"sources": [
			{
				"json": "KorvinagorCirclesOfTheLand",
				"abbreviation": "CotL",
				"full": "Circles of the Land",
				"authors": [
					"Korvinagor"
				],
				"convertedBy": [
					"Korvinagor"
				],
				"version": "1.0",
				"url": "https://homebrewery.naturalcrit.com/share/-nvhkEMSYKpd"
			}
		],
		"dateAdded": 1681474916,
		"dateLastModified": 1729630006,
		"_dateLastModifiedHash": "bc75029f1a",
		"edition": "classic"
	},
	"subclass": [
		{
			"name": "Circle of the Arctic",
			"source": "KorvinagorCirclesOfTheLand",
			"className": "Druid",
			"classSource": "PHB",
			"shortName": "Arctic",
			"subclassFeatures": [
				"Circle of the Arctic|Druid||Arctic|KorvinagorCirclesOfTheLand|2",
				"Subzero Aegis|Druid||Arctic|KorvinagorCirclesOfTheLand|6",
				"Frozen Resolve|Druid||Arctic|KorvinagorCirclesOfTheLand|10",
				"Inescapable Chill|Druid||Arctic|KorvinagorCirclesOfTheLand|14"
			],
			"subclassSpells": [
				"Ray of Frost",
				"Armor of Agathys",
				"Ice Knife|xge",
				"Gentle Repose",
				"Rime's Binding Ice|ftd",
				"Sleet Storm",
				"Slow",
				"Ice Storm",
				"Otiluke's Resilient Sphere",
				"Cone of Cold",
				"Hold Monster",
				"Wall of Ice"
			],
			"additionalSpells": [
				{
					"known": {
						"2": [
							"ray of frost"
						]
					},
					"prepared": {
						"2": [
							"armor of agathys",
							"ice knife|xge"
						],
						"3": [
							"gentle repose",
							"Rime's binding ice|ftd"
						],
						"5": [
							"sleet storm",
							"slow"
						],
						"7": [
							"ice storm",
							"Otiluke's resilient sphere"
						],
						"9": [
							"cone of cold",
							"hold monster"
						],
						"14": [
							"wall of ice"
						]
					}
				}
			]
		},
		{
			"name": "Circle of the Coast",
			"source": "KorvinagorCirclesOfTheLand",
			"className": "Druid",
			"classSource": "PHB",
			"shortName": "Coast",
			"subclassFeatures": [
				"Circle of the Coast|Druid||Coast|KorvinagorCirclesOfTheLand|2",
				"Bend the Waves|Druid||Coast|KorvinagorCirclesOfTheLand|6",
				"Ebb and Flow|Druid||Coast|KorvinagorCirclesOfTheLand|10",
				"Mutable Current|Druid||Coast|KorvinagorCirclesOfTheLand|14"
			],
			"subclassSpells": [
				"Shape Water|xge",
				"Absorb Elements|xge",
				"Thunderwave",
				"Mirror Image",
				"Misty Step",
				"Tidal Wave|xge",
				"Wall of Water|xge",
				"Control Water",
				"Watery Sphere|xge",
				"Maelstrom|xge",
				"Scrying"
			],
			"additionalSpells": [
				{
					"known": {
						"2": [
							"shape water|xge"
						]
					},
					"prepared": {
						"2": [
							"absorb elements|xge",
							"thunderwave"
						],
						"3": [
							"mirror image",
							"misty step"
						],
						"5": [
							"tidal wave|xge",
							"wall of water|xge"
						],
						"7": [
							"control water",
							"watery sphere|xge"
						],
						"9": [
							"maelstrom|xge",
							"scrying"
						]
					}
				}
			]
		},
		{
			"name": "Circle of the Desert",
			"source": "KorvinagorCirclesOfTheLand",
			"className": "Druid",
			"classSource": "PHB",
			"shortName": "Desert",
			"subclassFeatures": [
				"Circle of the Desert|Druid||Desert|KorvinagorCirclesOfTheLand|2",
				"Shifting Dunes|Druid||Desert|KorvinagorCirclesOfTheLand|6",
				"Veil of Sand|Druid||Desert|KorvinagorCirclesOfTheLand|10",
				"Illusory Desolation|Druid||Desert|KorvinagorCirclesOfTheLand|14"
			],
			"subclassSpells": [
				"Minor Illusion",
				"Disguise Self",
				"Silent Image",
				"Blur",
				"Vortex Warp|scc",
				"Major Image",
				"Wall of Sand|xge",
				"Banishment",
				"Hallucinatory Terrain",
				"Dawn|xge",
				"Seeming",
				"Mirage Arcane"
			],
			"additionalSpells": [
				{
					"known": {
						"2": [
							"minor illusion"
						]
					},
					"prepared": {
						"2": [
							"disguise self",
							"silent image"
						],
						"3": [
							"blur",
							"vortex warp|scc"
						],
						"5": [
							"major image",
							"wall of sand|xge"
						],
						"7": [
							"banishment",
							"hallucinatory terrain"
						],
						"9": [
							"dawn|xge",
							"seeming"
						],
						"14": [
							"mirage arcane"
						]
					}
				}
			]
		},
		{
			"name": "Circle of the Forest",
			"source": "KorvinagorCirclesOfTheLand",
			"className": "Druid",
			"classSource": "PHB",
			"shortName": "Forest",
			"subclassFeatures": [
				"Circle of the Forest|Druid||Forest|KorvinagorCirclesOfTheLand|2",
				"Friend of the Forest|Druid||Forest|KorvinagorCirclesOfTheLand|6",
				"Heart of the Woods|Druid||Forest|KorvinagorCirclesOfTheLand|10",
				"Steelbark Protector|Druid||Forest|KorvinagorCirclesOfTheLand|14"
			],
			"subclassSpells": [
				"Thorn Whip",
				"Entangle",
				"Sanctuary",
				"Barkskin",
				"Spike Growth",
				"Lightning Bolt",
				"Plant Growth",
				"Conjure Woodland Beings",
				"Fire Shield",
				"Tree Stride",
				"Wrath of Nature|xge"
			],
			"additionalSpells": [
				{
					"known": {
						"2": [
							"thorn whip"
						]
					},
					"prepared": {
						"2": [
							"entangle",
							"sanctuary"
						],
						"3": [
							"barkskin",
							"spike growth"
						],
						"5": [
							"lightning bolt",
							"plant growth"
						],
						"7": [
							"conjure woodland beings",
							"fire shield"
						],
						"9": [
							"tree stride",
							"wrath of nature|xge"
						]
					}
				}
			]
		},
		{
			"name": "Circle of the Grassland",
			"source": "KorvinagorCirclesOfTheLand",
			"className": "Druid",
			"classSource": "PHB",
			"shortName": "Grassland",
			"subclassFeatures": [
				"Circle of the Grassland|Druid||Grassland|KorvinagorCirclesOfTheLand|2",
				"Natural Celerity|Druid||Grassland|KorvinagorCirclesOfTheLand|6",
				"Rapid Regrowth|Druid||Grassland|KorvinagorCirclesOfTheLand|10",
				"Spell Proliferation|Druid||Grassland|KorvinagorCirclesOfTheLand|14"
			],
			"subclassSpells": [
				"Message",
				"Gift of Alacrity|egw",
				"Longstrider",
				"Invisibility",
				"Pass Without Trace",
				"Haste",
				"Sending",
				"Dimension Door",
				"Divination",
				"Dream",
				"Steel Wind Strike|xge"
			],
			"additionalSpells": [
				{
					"known": {
						"2": [
							"message"
						]
					},
					"prepared": {
						"2": [
							"gift of alacrity|egw",
							"longstrider"
						],
						"3": [
							"invisibility",
							"pass without trace"
						],
						"5": [
							"haste",
							"sending"
						],
						"7": [
							"dimension door",
							"divination"
						],
						"9": [
							"dream",
							"steel wind strike|xge"
						]
					}
				}
			]
		},
		{
			"name": "Circle of the Mountain",
			"source": "KorvinagorCirclesOfTheLand",
			"className": "Druid",
			"classSource": "PHB",
			"shortName": "Mountain",
			"subclassFeatures": [
				"Circle of the Mountain|Druid||Mountain|KorvinagorCirclesOfTheLand|2",
				"Earth's Ascent|Druid||Mountain|KorvinagorCirclesOfTheLand|6",
				"Esteemed Authority|Druid||Mountain|KorvinagorCirclesOfTheLand|10",
				"Unshakable Fortitude|Druid||Mountain|KorvinagorCirclesOfTheLand|14"
			],
			"subclassSpells": [
				"Booming Blade|tce",
				"Command",
				"Shield",
				"Immovable Object|egw",
				"Shatter",
				"Counterspell",
				"Fly",
				"Stoneskin",
				"Storm Sphere|xge",
				"Destructive Wave",
				"Wall of Stone"
			],
			"additionalSpells": [
				{
					"known": {
						"2": [
							"booming blade|tce"
						]
					},
					"prepared": {
						"2": [
							"command",
							"shield"
						],
						"3": [
							"immovable object|egw",
							"shatter"
						],
						"5": [
							"counterspell",
							"fly"
						],
						"7": [
							"stoneskin",
							"storm sphere|xge"
						],
						"9": [
							"destructive wave",
							"wall of stone"
						]
					}
				}
			]
		},
		{
			"name": "Circle of the Swamp",
			"source": "KorvinagorCirclesOfTheLand",
			"className": "Druid",
			"classSource": "PHB",
			"shortName": "Swamp",
			"subclassFeatures": [
				"Circle of the Swamp|Druid||Swamp|KorvinagorCirclesOfTheLand|2",
				"Hidden Peril|Druid||Swamp|KorvinagorCirclesOfTheLand|6",
				"Viral Inoculation|Druid||Swamp|KorvinagorCirclesOfTheLand|10",
				"Will-o'-the-Wisp|Druid||Swamp|KorvinagorCirclesOfTheLand|14"
			],
			"subclassSpells": [
				"Primal Savagery|xge",
				"Faerie Fire",
				"Fog Cloud",
				"Blindness/Deafness",
				"Suggestion",
				"Stinking Cloud",
				"Water Walk",
				"Compulsion",
				"Freedom of Movement",
				"Cloudkill",
				"Transmute Rock|xge",
				"Mislead"
			],
			"additionalSpells": [
				{
					"known": {
						"2": [
							"primal savagery|xge"
						]
					},
					"prepared": {
						"2": [
							"faerie fire",
							"fog cloud"
						],
						"3": [
							"blindness/deafness",
							"suggestion"
						],
						"5": [
							"stinking cloud",
							"water walk"
						],
						"7": [
							"compulsion",
							"freedom of movement"
						],
						"9": [
							"cloudkill",
							"transmute rock|xge"
						],
						"14": [
							"mislead"
						]
					}
				}
			]
		},
		{
			"name": "Circle of the Underdark",
			"source": "KorvinagorCirclesOfTheLand",
			"className": "Druid",
			"classSource": "PHB",
			"shortName": "Underdark",
			"subclassFeatures": [
				"Circle of the Underdark|Druid||Underdark|KorvinagorCirclesOfTheLand|2",
				"Eyeless Sight|Druid||Underdark|KorvinagorCirclesOfTheLand|6",
				"Sense the Subconcious|Druid||Underdark|KorvinagorCirclesOfTheLand|10",
				"Breathless Speech|Druid||Underdark|KorvinagorCirclesOfTheLand|14"
			],
			"subclassSpells": [
				"Mind Sliver|tce",
				"Dissonant Whispers",
				"Tasha's Hideous Laughter",
				"Calm Emotions",
				"Darkness",
				"Fear",
				"Gaseous Form",
				"Greater Invisibility",
				"Stone Shape",
				"Telekinesis",
				"Rary's Telepathic Bond",
				"Detect Thoughts"
			],
			"additionalSpells": [
				{
					"known": {
						"2": [
							"mind sliver|tce"
						]
					},
					"prepared": {
						"2": [
							"dissonant whispers",
							"Tasha's hideous laughter"
						],
						"3": [
							"calm emotions",
							"darkness"
						],
						"5": [
							"fear",
							"gaseous form"
						],
						"7": [
							"greater invisibility",
							"stone shape"
						],
						"9": [
							"telekinesis",
							"Rary's telepathic bond"
						],
						"10": [
							"detect thoughts"
						]
					}
				}
			]
		}
	],
	"subclassFeature": [
		{
			"name": "Circle of the Arctic",
			"source": "KorvinagorCirclesOfTheLand",
			"className": "Druid",
			"classSource": "PHB",
			"subclassShortName": "Arctic",
			"subclassSource": "KorvinagorCirclesOfTheLand",
			"level": 2,
			"entries": [
				"Druids of the Circle of the Arctic hail from lands steeped in the cold, from tundras to polar regions alike. Reflecting the harshness of life there, these druids epitomize the tenets of stoicism and endurance, wielding the chill for both offensive and defensive purposes.",
				{
					"type": "refSubclassFeature",
					"subclassFeature": "Circle Spells|Druid||Arctic|KorvinagorCirclesOfTheLand|2"
				},
				{
					"type": "refSubclassFeature",
					"subclassFeature": "Frigid Recovery|Druid||Arctic|KorvinagorCirclesOfTheLand|2"
				}
			]
		},
		{
			"name": "Circle Spells",
			"source": "KorvinagorCirclesOfTheLand",
			"className": "Druid",
			"classSource": "PHB",
			"subclassShortName": "Arctic",
			"subclassSource": "KorvinagorCirclesOfTheLand",
			"level": 2,
			"header": 1,
			"entries": [
				"{@i 2nd-level Circle of the Arctic feature}",
				"Drawing power from the frigid poles grants you access to spells that protect and hinder. You learn the {@spell ray of frost} cantrip.",
				"When you reach certain Druid levels, you gain access to the spells in the table below. They count as Druid spells for you, and you always have them prepared, but they don't count against the total number of spells you prepare each day.",
				{
					"type": "table",
					"caption": "Circle of the Arctic Spells",
					"colLabels": [
						"Druid Level",
						"Spells"
					],
					"colStyles": [
						"col-2 text-center",
						"col-10"
					],
					"rows": [
						[
							"2nd",
							"{@spell armor of agathys}, {@spell ice knife|xge}"
						],
						[
							"3rd",
							"{@spell gentle repose}, {@spell rime's binding ice|ftd}"
						],
						[
							"5th",
							"{@spell sleet storm}, {@spell slow}"
						],
						[
							"7th",
							"{@spell ice storm}, {@spell otiluke's resilient sphere}"
						],
						[
							"9th",
							"{@spell cone of cold}, {@spell hold monster}"
						]
					]
				}
			]
		},
		{
			"name": "Frigid Recovery",
			"source": "KorvinagorCirclesOfTheLand",
			"className": "Druid",
			"classSource": "PHB",
			"subclassShortName": "Arctic",
			"subclassSource": "KorvinagorCirclesOfTheLand",
			"level": 2,
			"header": 1,
			"entries": [
				"{@i 2nd-level Circle of the Arctic feature}",
				"You can recover some of your druidic magic by communing with the frost and snow. During a short rest, you choose expended spell slots to recover. The spell slots can have a combined level that is equal to or less than half your druid level (rounded up), and none of the slots can be 6th level or higher.",
				"If you use this feature in an arctic environment, you can increase this combined level by one. You can't use this feature again until you finish a long rest."
			]
		},
		{
			"name": "Subzero Aegis",
			"source": "KorvinagorCirclesOfTheLand",
			"className": "Druid",
			"classSource": "PHB",
			"subclassShortName": "Arctic",
			"subclassSource": "KorvinagorCirclesOfTheLand",
			"level": 6,
			"header": 2,
			"entries": [
				"{@i 6th-level Circle of the Arctic feature}",
				"You learn to instinctively channel the protective aspects of ice. As a reaction when you take damage, you can expend a spell slot to cast {@spell armor of agathys} at the equivalent level.",
				"Additionally, as part of this reaction, you can expend a Wild Shape usage to increase the amount of temporary hit points that this casting of the spell grants by three times your Druid level."
			]
		},
		{
			"name": "Frozen Resolve",
			"source": "KorvinagorCirclesOfTheLand",
			"className": "Druid",
			"classSource": "PHB",
			"subclassShortName": "Arctic",
			"subclassSource": "KorvinagorCirclesOfTheLand",
			"level": 10,
			"header": 2,
			"entries": [
				"{@i 10th-level Circle of the Arctic feature}",
				"The magic you channel becomes enduring as the life at the poles: persisting despite severe hardship. While concentrating on a spell, you have advantage on Constitution saving throws.",
				"Additionally, when you cast the spell {@spell ice storm}, you can choose to have its difficult terrain last for 1 minute."
			]
		},
		{
			"name": "Inescapable Chill",
			"source": "KorvinagorCirclesOfTheLand",
			"className": "Druid",
			"classSource": "PHB",
			"subclassShortName": "Arctic",
			"subclassSource": "KorvinagorCirclesOfTheLand",
			"level": 14,
			"header": 2,
			"entries": [
				"{@i 14th-level Circle of the Arctic feature}",
				"Your magic becomes capable of suffusing your foes with additional lethargy. Whenever a creature takes cold damage from your spells, it must succeed on a Constitution saving throw against your spell save DC or have its speed halved until the start of your next turn.",
				"You can also cast {@spell wall of ice} without expending a spell slot once per long rest, and it is always prepared for you."
			]
		},
		{
			"name": "Circle of the Coast",
			"source": "KorvinagorCirclesOfTheLand",
			"className": "Druid",
			"classSource": "PHB",
			"subclassShortName": "Coast",
			"subclassSource": "KorvinagorCirclesOfTheLand",
			"level": 2,
			"entries": [
				"Some of the most flexible druids belong to the Circle of the Coast, for the shifting tides and shoals that empower them are much the same in temperament. Espousing a philosophy of change, they smoothly adjust to any situation, just like the lands they preside over.",
				{
					"type": "refSubclassFeature",
					"subclassFeature": "Circle Spells|Druid||Coast|KorvinagorCirclesOfTheLand|2"
				},
				{
					"type": "refSubclassFeature",
					"subclassFeature": "Tidal Recovery|Druid||Coast|KorvinagorCirclesOfTheLand|2"
				}
			]
		},
		{
			"name": "Circle Spells",
			"source": "KorvinagorCirclesOfTheLand",
			"className": "Druid",
			"classSource": "PHB",
			"subclassShortName": "Coast",
			"subclassSource": "KorvinagorCirclesOfTheLand",
			"level": 2,
			"header": 1,
			"entries": [
				"{@i 2nd-level Circle of the Coast feature}",
				"Your affinity to oceanic water grants you spells to channel it. You learn the {@spell shape water|xge} cantrip. The cantrip can affect a larger area when you reach 5th level (10-foot cube), 11th level (15-foot cube), and 17th level (20-foot cube).",
				"When you reach certain Druid levels, you gain access to the spells in the table below. They count as Druid spells for you, and you always have them prepared, but they don't count against the total number of spells you prepare each day.",
				{
					"type": "table",
					"caption": "Circle of the Coast Spells",
					"colLabels": [
						"Druid Level",
						"Spells"
					],
					"colStyles": [
						"col-2 text-center",
						"col-10"
					],
					"rows": [
						[
							"2nd",
							"{@spell absorb elements|xge}, {@spell thunderwave}"
						],
						[
							"3rd",
							"{@spell mirror image}, {@spell misty step}"
						],
						[
							"5th",
							"{@spell tidal wave|xge}, {@spell wall of water|xge}"
						],
						[
							"7th",
							"{@spell control water}, {@spell watery sphere|xge}"
						],
						[
							"9th",
							"{@spell maelstrom|xge}, {@spell scrying}"
						]
					]
				}
			]
		},
		{
			"name": "Tidal Recovery",
			"source": "KorvinagorCirclesOfTheLand",
			"className": "Druid",
			"classSource": "PHB",
			"subclassShortName": "Coast",
			"subclassSource": "KorvinagorCirclesOfTheLand",
			"level": 2,
			"header": 1,
			"entries": [
				"{@i 2nd-level Circle of the Coast feature}",
				"You can recover some of your druidic magic by communing with the sea and shore. During a short rest, you choose expended spell slots to recover. The spell slots can have a combined level that is equal to or less than half your druid level (rounded up), and none of the slots can be 6th level or higher.",
				"If you use this feature in a coastal or aquatic environment, you can increase this combined level by one. You can't use this feature again until you finish a long rest."
			]
		},
		{
			"name": "Bend the Waves",
			"source": "KorvinagorCirclesOfTheLand",
			"className": "Druid",
			"classSource": "PHB",
			"subclassShortName": "Coast",
			"subclassSource": "KorvinagorCirclesOfTheLand",
			"level": 6,
			"header": 2,
			"entries": [
				"{@i 6th-level Circle of the Coast feature}",
				"Your spells become as flexible as the waters they harness, letting you divert their impact away from allies and alter their properties.",
				"Whenever you cast a spell from your Circle Spell list, you can choose any number of creatures that you can see. They automatically succeed on any checks or saving throws against the spell, and take no damage from them.",
				"Additionally, whenever a creature attempts to enter a {@spell wall of water|xge} you create, it must succeed on a Strength check against your spell save DC or become unable to pass through the wall until its next turn.",
				"If the wall cuts through a creature's space when it appears, the creature must succeed on a Strength saving throw against your spell save DC or be pushed to one side of it (your choice which side)."
			]
		},
		{
			"name": "Ebb and Flow",
			"source": "KorvinagorCirclesOfTheLand",
			"className": "Druid",
			"classSource": "PHB",
			"subclassShortName": "Coast",
			"subclassSource": "KorvinagorCirclesOfTheLand",
			"level": 10,
			"header": 2,
			"entries": [
				"{@i 10th-level Circle of the Coast feature}",
				"Like the rising and falling tide, your spells are in constant motion, moving to fit the situation.",
				"While concentrating on the spell {@spell maelstrom|xge}, you can use your action to cause the area to reappear elsewhere on the ground up to 60 feet away from its previous spot. Additionally, if a creature succeeds on the spell's saving throw, it still takes half damage. You can also move the effect of {@spell watery sphere|xge} using a bonus action.",
				"Finally, when you cast {@spell wall of water|xge} using a spell slot of 5th level or higher, its maximum dimensions are tripled. You can also form the wall into a hemisphere with a diameter of up to 30 feet and turn the wall opaque."
			]
		},
		{
			"name": "Mutable Current",
			"source": "KorvinagorCirclesOfTheLand",
			"className": "Druid",
			"classSource": "PHB",
			"subclassShortName": "Coast",
			"subclassSource": "KorvinagorCirclesOfTheLand",
			"level": 14,
			"header": 2,
			"entries": [
				"{@i 14th-level Circle of the Coast feature}",
				"You learn to impart the flexibility of water to the rest of your magic. You can expend two Wild Shape usages as part of casting a spell that isn't from your Circle Spell list to apply the effects of your 6th level feature to it.",
				"Additionally, if the spell you cast is {@spell tsunami}, its casting time becomes 1 action instead of 1 minute, and can also affect Gargantuan creatures on subsequent turns."
			]
		},
		{
			"name": "Circle of the Desert",
			"source": "KorvinagorCirclesOfTheLand",
			"className": "Druid",
			"classSource": "PHB",
			"subclassShortName": "Desert",
			"subclassSource": "KorvinagorCirclesOfTheLand",
			"level": 2,
			"entries": [
				"To many, the arid wastelands are bleak, monotonous places of death. But the druids who inhabit them know that not everything is as it seems: life hides here in the most unlikely of places, often just out of sight. These druids are just as elusive, using their magic to spirit themselves or even hostile visitors away and produce dizzying mirages, acting both as protectors of the desert and extensions of it.",
				{
					"type": "refSubclassFeature",
					"subclassFeature": "Circle Spells|Druid||Desert|KorvinagorCirclesOfTheLand|2"
				},
				{
					"type": "refSubclassFeature",
					"subclassFeature": "Torrid Recovery|Druid||Desert|KorvinagorCirclesOfTheLand|2"
				}
			]
		},
		{
			"name": "Circle Spells",
			"source": "KorvinagorCirclesOfTheLand",
			"className": "Druid",
			"classSource": "PHB",
			"subclassShortName": "Desert",
			"subclassSource": "KorvinagorCirclesOfTheLand",
			"level": 2,
			"header": 1,
			"entries": [
				"{@i 2nd-level Circle of the Desert feature}",
				"Your connection to the desert sands grants you access to certain spells. You learn the {@spell minor illusion} cantrip.",
				"When you reach certain Druid levels, you gain access to the spells in the table below. They count as Druid spells for you, and you always have them prepared, but they don't count against the total number of spells you prepare each day.",
				{
					"type": "table",
					"caption": "Circle of the Desert Spells",
					"colLabels": [
						"Druid Level",
						"Spells"
					],
					"colStyles": [
						"col-2 text-center",
						"col-10"
					],
					"rows": [
						[
							"2nd",
							"{@spell disguise self}, {@spell silent image}"
						],
						[
							"3rd",
							"{@spell blur}, {@spell vortex warp|scc}"
						],
						[
							"5th",
							"{@spell major image}, {@spell wall of sand|xge}"
						],
						[
							"7th",
							"{@spell banishment}, {@spell hallucinatory terrain}"
						],
						[
							"9th",
							"{@spell dawn|xge}, {@spell seeming}"
						]
					]
				}
			]
		},
		{
			"name": "Torrid Recovery",
			"source": "KorvinagorCirclesOfTheLand",
			"className": "Druid",
			"classSource": "PHB",
			"subclassShortName": "Desert",
			"subclassSource": "KorvinagorCirclesOfTheLand",
			"level": 2,
			"header": 1,
			"entries": [
				"{@i 2nd-level Circle of the Desert feature}",
				"You can recover some of your druidic magic by communing with the dunes and sands. During a short rest, you choose expended spell slots to recover. The spell slots can have a combined level that is equal to or less than half your druid level (rounded up), and none of the slots can be 6th level or higher.",
				"If you use this feature in a desert environment, you can increase this combined level by one. You can't use this feature again until you finish a long rest."
			]
		},
		{
			"name": "Shifting Dunes",
			"source": "KorvinagorCirclesOfTheLand",
			"className": "Druid",
			"classSource": "PHB",
			"subclassShortName": "Desert",
			"subclassSource": "KorvinagorCirclesOfTheLand",
			"level": 6,
			"header": 2,
			"entries": [
				"{@i 6th-level Circle of the Desert feature}",
				"Like the desert itself, your magic belies the senses, able to take on forms that can easily disorient those unfamiliar with it.",
				"While an illusion spell you have cast is active, you can recast that spell without expending a spell slot, ending the previous effect, but inheriting any expended duration.",
				"Additionally, while concentrating on {@spell wall of sand|xge}, you can use your action to make it reappear on the ground up to 60 feet away from its previous location."
			]
		},
		{
			"name": "Veil of Sand",
			"source": "KorvinagorCirclesOfTheLand",
			"className": "Druid",
			"classSource": "PHB",
			"subclassShortName": "Desert",
			"subclassSource": "KorvinagorCirclesOfTheLand",
			"level": 10,
			"header": 2,
			"entries": [
				"{@i 10th-level Circle of the Desert feature}",
				"As a bonus action, you can force a creature that you can see to succeed on a Dexterity saving throw against your spell save DC or have its surrounding area be {@quickref Vision and Light|PHB|2||heavily obscured} with swirling sand. This veil moves with the creature and lasts until the start of your next turn or if you dismiss it early (no action required)."
			]
		},
		{
			"name": "Illusory Desolation",
			"source": "KorvinagorCirclesOfTheLand",
			"className": "Druid",
			"classSource": "PHB",
			"subclassShortName": "Desert",
			"subclassSource": "KorvinagorCirclesOfTheLand",
			"level": 14,
			"header": 2,
			"entries": [
				"{@i 14th-level Circle of the Desert feature}",
				"You become capable of fully embodying the mysterious aspects of the sands, hiding the life that abounds in it from prying eyes with ease. You can cast {@spell blur} without using your concentration.",
				"Additionally, when you cast {@spell mirage arcane}, you can expend two Wild Shape usages to change its casting time to 1 action, and it is always prepared for you."
			]
		},
		{
			"name": "Circle of the Forest",
			"source": "KorvinagorCirclesOfTheLand",
			"className": "Druid",
			"classSource": "PHB",
			"subclassShortName": "Forest",
			"subclassSource": "KorvinagorCirclesOfTheLand",
			"level": 2,
			"entries": [
				"Druids of the Circle of the Forest are some of the most devoted to their land, considering themselves stewards of nature above all else, for no other place is as full of life as theirs. Their magic reflects this diversity, calling upon the forests and all the myriad phenomena within them down against those that would threaten it.",
				{
					"type": "refSubclassFeature",
					"subclassFeature": "Circle Spells|Druid||Forest|KorvinagorCirclesOfTheLand|2"
				},
				{
					"type": "refSubclassFeature",
					"subclassFeature": "Verdant Recovery|Druid||Forest|KorvinagorCirclesOfTheLand|2"
				}
			]
		},
		{
			"name": "Circle Spells",
			"source": "KorvinagorCirclesOfTheLand",
			"className": "Druid",
			"classSource": "PHB",
			"subclassShortName": "Forest",
			"subclassSource": "KorvinagorCirclesOfTheLand",
			"level": 2,
			"header": 1,
			"entries": [
				"{@i 2nd-level Circle of the Forest feature}",
				"The forests bestow you with a portion of their magic in the form of spells. You learn the {@spell thorn whip} cantrip.",
				"When you reach certain Druid levels, you gain access to the spells in the table below. They count as Druid spells for you, and you always have them prepared, but they don't count against the total number of spells you prepare each day.",
				{
					"type": "table",
					"caption": "Circle of the Forest Spells",
					"colLabels": [
						"Druid Level",
						"Spells"
					],
					"colStyles": [
						"col-2 text-center",
						"col-10"
					],
					"rows": [
						[
							"2nd",
							"{@spell entangle}, {@spell sanctuary}"
						],
						[
							"3rd",
							"{@spell barkskin}, {@spell spike growth}"
						],
						[
							"5th",
							"{@spell lightning bolt}, {@spell plant growth}"
						],
						[
							"7th",
							"{@spell conjure woodland beings}, {@spell fire shield}"
						],
						[
							"9th",
							"{@spell tree stride}, {@spell wrath of nature|xge}"
						]
					]
				}
			]
		},
		{
			"name": "Verdant Recovery",
			"source": "KorvinagorCirclesOfTheLand",
			"className": "Druid",
			"classSource": "PHB",
			"subclassShortName": "Forest",
			"subclassSource": "KorvinagorCirclesOfTheLand",
			"level": 2,
			"header": 1,
			"entries": [
				"{@i 2nd-level Circle of the Forest feature}",
				"You can recover some of your druidic magic by communing with the trees and undergrowth. During a short rest, you choose expended spell slots to recover. The spell slots can have a combined level that is equal to or less than half your druid level (rounded up), and none of the slots can be 6th level or higher.",
				"If you use this feature in a forest environment, you can increase this combined level by one. You can't use this feature again until you finish a long rest."
			]
		},
		{
			"name": "Friend of the Forest",
			"source": "KorvinagorCirclesOfTheLand",
			"className": "Druid",
			"classSource": "PHB",
			"subclassShortName": "Forest",
			"subclassSource": "KorvinagorCirclesOfTheLand",
			"level": 6,
			"header": 2,
			"entries": [
				"{@i 6th-level Circle of the Forest feature}",
				"Plant life recognises you as an ally, parting in your wake and allowing you to move through them effortlessly. You can pass through plants without being slowed or damaged by them if they are nonmagical, or if they are created or manipulated by you, and have advantage on checks and saving throws against plants that are magically created or manipulated to impede movement.",
				"In addition, if you cast {@spell entangle} using a 2nd level spell slot or higher, a creature that enters the affected area for the first time on a turn or starts its turn there must succeed on a Strength saving throw as if they were in the area when it was cast or suffer the same effects."
			]
		},
		{
			"name": "Heart of the Woods",
			"source": "KorvinagorCirclesOfTheLand",
			"className": "Druid",
			"classSource": "PHB",
			"subclassShortName": "Forest",
			"subclassSource": "KorvinagorCirclesOfTheLand",
			"level": 10,
			"header": 2,
			"entries": [
				"{@i 10th-level Circle of the Forest feature}",
				"You can tap into your own inner magic to bring the forest with you no matter where you go. As a bonus action, you can expend a Wild Shape usage to create a number of Medium trees up to your proficiency bonus or a single Large tree in any unoccupied space on the ground that you can see within 150 feet of you.",
				"The trees have a maximum height of 3 feet times your Druid level, and can be of any kind that you wish. They can have foliage grow underneath them in a 20-foot radius. If created in an area unsuitable for plant life, the trees and any accompanying foliage disappear after 24 hours."
			]
		},
		{
			"name": "Steelbark Protector",
			"source": "KorvinagorCirclesOfTheLand",
			"className": "Druid",
			"classSource": "PHB",
			"subclassShortName": "Forest",
			"subclassSource": "KorvinagorCirclesOfTheLand",
			"level": 14,
			"header": 2,
			"entries": [
				"{@i 14th-level Circle of the Forest feature}",
				"The forests entrust you with the strongest of their blessings. You can cast {@spell barkskin} and {@spell tree stride} without using your concentration. Additionally, if you cast barkskin in this way, at the start of each of the target's turns the target gains a number of temporary hit points equal to your Wisdom modifier plus your proficiency bonus until the spell ends."
			]
		},
		{
			"name": "Circle of the Grassland",
			"source": "KorvinagorCirclesOfTheLand",
			"className": "Druid",
			"classSource": "PHB",
			"subclassShortName": "Grassland",
			"subclassSource": "KorvinagorCirclesOfTheLand",
			"level": 2,
			"entries": [
				"Quiet and supportive, some of the most harmonious druids belong to the Circle of the Grassland, their magic and way of life an intimate reflection of the humble flora and fauna that they communicate with as kin: swift, resilient, and pervasive, but above all, interconnected.",
				{
					"type": "refSubclassFeature",
					"subclassFeature": "Circle Spells|Druid||Grassland|KorvinagorCirclesOfTheLand|2"
				},
				{
					"type": "refSubclassFeature",
					"subclassFeature": "Expansive Recovery|Druid||Grassland|KorvinagorCirclesOfTheLand|2"
				}
			]
		},
		{
			"name": "Circle Spells",
			"source": "KorvinagorCirclesOfTheLand",
			"className": "Druid",
			"classSource": "PHB",
			"subclassShortName": "Grassland",
			"subclassSource": "KorvinagorCirclesOfTheLand",
			"level": 2,
			"header": 1,
			"entries": [
				"{@i 2nd-level Circle of the Grassland feature}",
				"Your magic is touched by the sweeping plains, giving you access to spells that traverse distances, figurative and literal. You learn the {@spell message} cantrip.",
				"When you reach certain Druid levels, you gain access to the spells in the table below. They count as Druid spells for you, and you always have them prepared, but they don't count against the total number of spells you prepare each day.",
				{
					"type": "table",
					"caption": "Circle of the Grassland Spells",
					"colLabels": [
						"Druid Level",
						"Spells"
					],
					"colStyles": [
						"col-2 text-center",
						"col-10"
					],
					"rows": [
						[
							"2nd",
							"{@spell gift of alacrity|egw}, {@spell longstrider}"
						],
						[
							"3rd",
							"{@spell invisibility}, {@spell pass without trace}"
						],
						[
							"5th",
							"{@spell haste}, {@spell sending}"
						],
						[
							"7th",
							"{@spell dimension door}, {@spell divination}"
						],
						[
							"9th",
							"{@spell dream}, {@spell steel wind strike|xge}"
						]
					]
				}
			]
		},
		{
			"name": "Expansive Recovery",
			"source": "KorvinagorCirclesOfTheLand",
			"className": "Druid",
			"classSource": "PHB",
			"subclassShortName": "Grassland",
			"subclassSource": "KorvinagorCirclesOfTheLand",
			"level": 2,
			"header": 1,
			"entries": [
				"{@i 2nd-level Circle of the Grassland feature}",
				"You can recover some of your druidic magic by communing with the savannas and prairies. During a short rest, you choose expended spell slots to recover. The spell slots can have a combined level that is equal to or less than half your druid level (rounded up), and none of the slots can be 6th level or higher.",
				"If you use this feature in a grassland environment, you can increase this combined level by one. You can't use this feature again until you finish a long rest."
			]
		},
		{
			"name": "Natural Celerity",
			"source": "KorvinagorCirclesOfTheLand",
			"className": "Druid",
			"classSource": "PHB",
			"subclassShortName": "Grassland",
			"subclassSource": "KorvinagorCirclesOfTheLand",
			"level": 6,
			"header": 1,
			"entries": [
				"{@i 6th-level Circle of the Grassland feature}",
				"Your spells are bolstered by the swiftness necessary for life to thrive on open grassland, for its flat landscapes leave exposed creatures vulnerable to attack.",
				"When you cast a spell from your Circle Spell list that has a casting time of 1 action, you can change the casting time to 1 bonus action."
			]
		},
		{
			"name": "Rapid Regrowth",
			"source": "KorvinagorCirclesOfTheLand",
			"className": "Druid",
			"classSource": "PHB",
			"subclassShortName": "Grassland",
			"subclassSource": "KorvinagorCirclesOfTheLand",
			"level": 10,
			"header": 2,
			"entries": [
				"{@i 10th-level Circle of the Grassland feature}",
				"The short stature of grassland flora belies a hidden resilience, able to grow back time and time again despite numerous hardships. You become capable of tapping into a similar vitality yourself, partially healing recent injuries.",
				"You can expend a Wild Shape usage as an action to select a creature that you can see within 60 feet of you. It regains hit points equal to half of all hit points it lost since the end of its last turn (rounded up)."
			]
		},
		{
			"name": "Spell Proliferation",
			"source": "KorvinagorCirclesOfTheLand",
			"className": "Druid",
			"classSource": "PHB",
			"subclassShortName": "Grassland",
			"subclassSource": "KorvinagorCirclesOfTheLand",
			"level": 14,
			"header": 2,
			"entries": [
				"{@i 14th-level Circle of the Grassland feature}",
				"Your magic gains a semblance of life outside of you, letting it persist beyond your control. Whenever the effect of one of your spells with a duration of 1 minute or longer would end, you can have it do so at the end of your next turn instead."
			]
		},
		{
			"name": "Circle of the Mountain",
			"source": "KorvinagorCirclesOfTheLand",
			"className": "Druid",
			"classSource": "PHB",
			"subclassShortName": "Mountain",
			"subclassSource": "KorvinagorCirclesOfTheLand",
			"level": 2,
			"entries": [
				"High above the rest of the world, the most imperious of druids can be found in the Circle of the Mountain. Often serious or even regal in demeanour, many of them take great pride in their strength, their magic manifesting in similarly spectacular ways, both to instil awe and respect for the lands that they are responsible for balancing, and to demonstrate its overwhelming power to those who would desecrate it.",
				{
					"type": "refSubclassFeature",
					"subclassFeature": "Circle Spells|Druid||Mountain|KorvinagorCirclesOfTheLand|2"
				},
				{
					"type": "refSubclassFeature",
					"subclassFeature": "Lofty Recovery|Druid||Mountain|KorvinagorCirclesOfTheLand|2"
				}
			]
		},
		{
			"name": "Circle Spells",
			"source": "KorvinagorCirclesOfTheLand",
			"className": "Druid",
			"classSource": "PHB",
			"subclassShortName": "Mountain",
			"subclassSource": "KorvinagorCirclesOfTheLand",
			"level": 2,
			"header": 1,
			"entries": [
				"{@i 2nd-level Circle of the Mountain feature}",
				"Your connection to the world's highest points grants you access to spells that shake the earth and sky with your very presence. You learn the {@spell booming blade|tce} cantrip.",
				"When you reach certain Druid levels, you gain access to the spells in the table below. They count as Druid spells for you, and you always have them prepared, but they don't count against the total number of spells you prepare each day.",
				{
					"type": "table",
					"caption": "Circle of the Mountain Spells",
					"colLabels": [
						"Druid Level",
						"Spells"
					],
					"colStyles": [
						"col-2 text-center",
						"col-10"
					],
					"rows": [
						[
							"2nd",
							"{@spell command}, {@spell shield}"
						],
						[
							"3rd",
							"{@spell immovable object|egw}, {@spell shatter}"
						],
						[
							"5th",
							"{@spell counterspell}, {@spell fly}"
						],
						[
							"7th",
							"{@spell stoneskin}, {@spell storm sphere|xge}"
						],
						[
							"9th",
							"{@spell destructive wave}, {@spell wall of stone}"
						]
					]
				}
			]
		},
		{
			"name": "Lofty Recovery",
			"source": "KorvinagorCirclesOfTheLand",
			"className": "Druid",
			"classSource": "PHB",
			"subclassShortName": "Mountain",
			"subclassSource": "KorvinagorCirclesOfTheLand",
			"level": 2,
			"header": 1,
			"entries": [
				"{@i 2nd-level Circle of the Mountain feature}",
				"You can recover some of your druidic magic by communing with the alps and hills. During a short rest, you choose expended spell slots to recover. The spell slots can have a combined level that is equal to or less than half your druid level (rounded up), and none of the slots can be 6th level or higher.",
				"If you use this feature in a mountainous environment, you can increase this combined level by one. You can't use this feature again until you finish a long rest."
			]
		},
		{
			"name": "Earth's Ascent",
			"source": "KorvinagorCirclesOfTheLand",
			"className": "Druid",
			"classSource": "PHB",
			"subclassShortName": "Mountain",
			"subclassSource": "KorvinagorCirclesOfTheLand",
			"level": 6,
			"header": 2,
			"entries": [
				"{@i 6th-level Circle of the Mountain feature}",
				"The magic of the peaks lets you instil others with the power to aspire towards them. As a bonus action, you can touch a willing creature to grant them a flying speed of 60 feet until the end of your next turn, before safely descending as if under the effects of {@spell feather fall}.",
				"You can use this feature a number of times equal to your Wisdom modifier (minimum of once), and you regain all expended uses when you finish a long rest."
			]
		},
		{
			"name": "Esteemed Authority",
			"source": "KorvinagorCirclesOfTheLand",
			"className": "Druid",
			"classSource": "PHB",
			"subclassShortName": "Mountain",
			"subclassSource": "KorvinagorCirclesOfTheLand",
			"level": 10,
			"header": 2,
			"entries": [
				"{@i 10th-level Circle of the Mountain feature}",
				"Mountains tower over men like natural deities - you become capable of channelling this authority, compelling others to kneel before you in reverence.",
				"As part of casting a spell from your Circle Spell list, you can expend a Wild Shape usage. If you do so, whenever the spell deals damage to a creature, it must succeed on a Constitution saving throw against your spell save DC or have their speed become 0 until the end of their next turn and be knocked {@condition prone}.",
				"A creature that fails its Constitution saving throw while prone becomes {@condition stunned} until the end of its next turn instead."
			]
		},
		{
			"name": "Unshakable Fortitude",
			"source": "KorvinagorCirclesOfTheLand",
			"className": "Druid",
			"classSource": "PHB",
			"subclassShortName": "Mountain",
			"subclassSource": "KorvinagorCirclesOfTheLand",
			"level": 14,
			"header": 2,
			"entries": [
				"{@i 14th-level Circle of the Mountain feature}",
				"Like the mountains themselves, you can weather even the harshest of blows. You can cast {@spell stoneskin} without using your concentration or material components."
			]
		},
		{
			"name": "Circle of the Swamp",
			"source": "KorvinagorCirclesOfTheLand",
			"className": "Druid",
			"classSource": "PHB",
			"subclassShortName": "Swamp",
			"subclassSource": "KorvinagorCirclesOfTheLand",
			"level": 2,
			"entries": [
				"Often misunderstood and even reviled, druids of the Circle of the Swamp have a reputation for being pragmatic and deceptive, often using their magic in underhanded ways, from their use of poisons to their tendency to ambush foes. Many of these druids consider such tactics necessary: despite the many dangers the lands they protect possess, they know it is far more vulnerable to destruction than its appearance would suggest, but little understanding is given to life that can maim and kill, even if it too is trying to survive.",
				{
					"type": "refSubclassFeature",
					"subclassFeature": "Circle Spells|Druid||Swamp|KorvinagorCirclesOfTheLand|2"
				},
				{
					"type": "refSubclassFeature",
					"subclassFeature": "Hydric Recovery|Druid||Swamp|KorvinagorCirclesOfTheLand|2"
				}
			]
		},
		{
			"name": "Circle Spells",
			"source": "KorvinagorCirclesOfTheLand",
			"className": "Druid",
			"classSource": "PHB",
			"subclassShortName": "Swamp",
			"subclassSource": "KorvinagorCirclesOfTheLand",
			"level": 2,
			"header": 1,
			"entries": [
				"{@i 2nd-level Circle of the Swamp feature}",
				"Your connection to the water-saturated lands grants you access to magic that incapacitates and confuses. You learn the {@spell primal savagery|xge} cantrip.",
				"When you reach certain Druid levels, you gain access to the spells in the table below. They count as Druid spells for you, and you always have them prepared, but they don't count against the total number of spells you prepare each day.",
				{
					"type": "table",
					"caption": "Circle of the Swamp Spells",
					"colLabels": [
						"Druid Level",
						"Spells"
					],
					"colStyles": [
						"col-2 text-center",
						"col-10"
					],
					"rows": [
						[
							"2nd",
							"{@spell faerie fire}, {@spell fog cloud}"
						],
						[
							"3rd",
							"{@spell blindness/deafness}, {@spell suggestion}"
						],
						[
							"5th",
							"{@spell stinking cloud}, {@spell water walk}"
						],
						[
							"7th",
							"{@spell compulsion}, {@spell freedom of movement}"
						],
						[
							"9th",
							"{@spell cloudkill}, {@spell transmute rock|xge}"
						]
					]
				}
			]
		},
		{
			"name": "Hydric Recovery",
			"source": "KorvinagorCirclesOfTheLand",
			"className": "Druid",
			"classSource": "PHB",
			"subclassShortName": "Swamp",
			"subclassSource": "KorvinagorCirclesOfTheLand",
			"level": 2,
			"header": 1,
			"entries": [
				"{@i 2nd-level Circle of the Swamp feature}",
				"You can recover some of your druidic magic by communing with the bogs and marshes. During a short rest, you choose expended spell slots to recover. The spell slots can have a combined level that is equal to or less than half your druid level (rounded up), and none of the slots can be 6th level or higher.",
				"If you use this feature in a swamp environment, you can increase this combined level by one. You can't use this feature again until you finish a long rest."
			]
		},
		{
			"name": "Hidden Peril",
			"source": "KorvinagorCirclesOfTheLand",
			"className": "Druid",
			"classSource": "PHB",
			"subclassShortName": "Swamp",
			"subclassSource": "KorvinagorCirclesOfTheLand",
			"level": 6,
			"header": 2,
			"entries": [
				"{@i 6th-level Circle of the Swamp feature}",
				"You learn to use the element of surprise to more easily debilitate your foes. Creatures that are unable to see or hear you must make any checks or saving throws against your spells at disadvantage.",
				"Additionally, the speed of any creature that fails its saving throw against a {@spell stinking cloud} or {@spell cloudkill} you create becomes 0 until the start of its next turn."
			]
		},
		{
			"name": "Viral Inoculation",
			"source": "KorvinagorCirclesOfTheLand",
			"className": "Druid",
			"classSource": "PHB",
			"subclassShortName": "Swamp",
			"subclassSource": "KorvinagorCirclesOfTheLand",
			"level": 10,
			"header": 2,
			"entries": [
				"{@i 10th-level Circle of the Swamp feature}",
				"Constant exposure to the wetlands has left you stronger against its denizens and perils. You have a +2 bonus to saving throws against being {@condition charmed} or {@condition frightened}, and are immune to poison and disease."
			]
		},
		{
			"name": "Will-o'-the-Wisp",
			"source": "KorvinagorCirclesOfTheLand",
			"className": "Druid",
			"classSource": "PHB",
			"subclassShortName": "Swamp",
			"subclassSource": "KorvinagorCirclesOfTheLand",
			"level": 14,
			"header": 2,
			"entries": [
				"{@i 14th-level Circle of the Swamp feature}",
				"You become capable of vanishing in the face of danger, leaving foes swinging at apparitions. You can expend a Wild Shape usage to cast {@spell mislead} as a reaction to a spell or attack roll without using your concentration.",
				"As part of this reaction, you can attempt to hide and move a distance up to your speed. If this movement causes you to leave the range of the spell or attack, you avoid its effects, your illusory double appearing as if it received it in your stead.",
				"Once you use this feature, you can't use it again until you finish a short or long rest."
			]
		},
		{
			"name": "Circle of the Underdark",
			"source": "KorvinagorCirclesOfTheLand",
			"className": "Druid",
			"classSource": "PHB",
			"subclassShortName": "Underdark",
			"subclassSource": "KorvinagorCirclesOfTheLand",
			"level": 2,
			"entries": [
				"Drawing strength from the caves and caverns under the earth, druids of the Circle of the Underdark wield magic shaped by this alien environment, manifesting both as physical adaptations and even psychic abilities, mirroring some of the denizens residing deep below.",
				"While much of the life here is hostile and strange, many of these druids still do their best to mediate it. Some of them are even said to guide lost travellers back to safety, or if they are feeling less charitable, terrifying them away with their deepest fears, reading their innermost thoughts as effortlessly as any aberration.",
				{
					"type": "refSubclassFeature",
					"subclassFeature": "Circle Spells|Druid||Underdark|KorvinagorCirclesOfTheLand|2"
				},
				{
					"type": "refSubclassFeature",
					"subclassFeature": "Subterranean Recovery|Druid||Underdark|KorvinagorCirclesOfTheLand|2"
				}
			]
		},
		{
			"name": "Circle Spells",
			"source": "KorvinagorCirclesOfTheLand",
			"className": "Druid",
			"classSource": "PHB",
			"subclassShortName": "Underdark",
			"subclassSource": "KorvinagorCirclesOfTheLand",
			"level": 2,
			"header": 1,
			"entries": [
				"{@i 2nd-level Circle of the Underdark feature}",
				"Your gain access to magics over the physical and mental darkness lurking underneath the surface of the normal world. You learn the {@spell mind sliver|tce} cantrip.",
				"When you reach certain Druid levels, you gain access to the spells in the table below. They count as Druid spells for you, and you always have them prepared, but they don't count against the total number of spells you prepare each day.",
				{
					"type": "table",
					"caption": "Circle of the Underdark Spells",
					"colLabels": [
						"Druid Level",
						"Spells"
					],
					"colStyles": [
						"col-2 text-center",
						"col-10"
					],
					"rows": [
						[
							"2nd",
							"{@spell dissonant whispers}, {@spell tasha's hideous laughter}"
						],
						[
							"3rd",
							"{@spell calm emotions}, {@spell darkness}"
						],
						[
							"5th",
							"{@spell fear}, {@spell gaseous form}"
						],
						[
							"7th",
							"{@spell greater invisibility}, {@spell stone shape}"
						],
						[
							"9th",
							"{@spell rary's telepathic bond}, {@spell telekinesis}"
						]
					]
				}
			]
		},
		{
			"name": "Subterranean Recovery",
			"source": "KorvinagorCirclesOfTheLand",
			"className": "Druid",
			"classSource": "PHB",
			"subclassShortName": "Underdark",
			"subclassSource": "KorvinagorCirclesOfTheLand",
			"level": 2,
			"header": 1,
			"entries": [
				"{@i 2nd-level Circle of the Underdark feature}",
				"You can recover some of your druidic magic by communing with the cavernous depths. During a short rest, you choose expended spell slots to recover. The spell slots can have a combined level that is equal to or less than half your druid level (rounded up), and none of the slots can be 6th level or higher.",
				"If you use this feature in an underground environment, you can increase this combined level by one. You can't use this feature again until you finish a long rest."
			]
		},
		{
			"name": "Eyeless Sight",
			"source": "KorvinagorCirclesOfTheLand",
			"className": "Druid",
			"classSource": "PHB",
			"subclassShortName": "Underdark",
			"subclassSource": "KorvinagorCirclesOfTheLand",
			"level": 6,
			"header": 2,
			"entries": [
				"{@i 6th-level Circle of the Underdark feature}",
				"The things that crawl throughout caves and caverns have no need for light to see, and you are no exception. As a bonus action, you can expend a Wild Shape usage to touch a willing creature and grant them {@quickref Blindsight|PHB|2||blindsight} out to a range of 15 feet for 1 hour."
			]
		},
		{
			"name": "Sense the Subconcious",
			"source": "KorvinagorCirclesOfTheLand",
			"className": "Druid",
			"classSource": "PHB",
			"subclassShortName": "Underdark",
			"subclassSource": "KorvinagorCirclesOfTheLand",
			"level": 10,
			"header": 2,
			"entries": [
				"{@i 10th-level Circle of the Underdark feature}",
				"You learn to treat the mind like a network of caves and caverns, letting you delve into the very hearts of others as easily as you do the underground.",
				"You can cast {@spell detect thoughts} without using your concentration, spell slots, or components, and can reach its effect out to creatures up to 60 feet away. Wisdom is your spellcasting ability for this spell.",
				"Additionally, if you read a creature's thoughts that you can't see, you become capable of seeing it until the spell ends, or if you shift your attention to another creature.",
				"You can use this feature a number of times equal to your proficiency bonus, and you regain all expended uses when you finish a long rest."
			]
		},
		{
			"name": "Breathless Speech",
			"source": "KorvinagorCirclesOfTheLand",
			"className": "Druid",
			"classSource": "PHB",
			"subclassShortName": "Underdark",
			"subclassSource": "KorvinagorCirclesOfTheLand",
			"level": 14,
			"header": 2,
			"entries": [
				"{@i 14th-level Circle of the Underdark feature}",
				"You become capable of drawing on some of your magic even while robbed of air. You can cast spells granted by your Druid subclass features without requiring any spell components, and can hold your breath indefinitely."
			]
		}
	]
}
